{
  "id": "859",
  "name": "{{ faker.name.last_name }}",
  "startAt": "270",
  "endAt": "549",
  "timezone": {
    "id": "551",
    "name": "{{ faker.name.last_name }}"
  },
  "description": "Auto Loan Account Handcrafted Concrete Chips",
  "accepts": [
    {
      "day": 537,
      "startTimeOfDay": 985,
      "endTimeOfDay": 585,
      "disabled": false
    },
    {
      "day": 866,
      "startTimeOfDay": 519,
      "endTimeOfDay": 538,
      "disabled": true
    }
  ],
  "excepts": [
    {
      "name": "{{ faker.name.last_name }}",
      "date": "17",
      "repeat": true,
      "disabled": true,
      "working": false,
      "workStart": 491,
      "workStop": 202
    },
    {
      "name": "{{ faker.name.last_name }}",
      "date": "658",
      "repeat": true,
      "disabled": false,
      "working": true,
      "workStart": 669,
      "workStop": 725
    }
  ],
  "domainId": "884",
  "specials": [
    {
      "day": 640,
      "startTimeOfDay": 724,
      "endTimeOfDay": 997,
      "disabled": true
    },
    {
      "day": 959,
      "startTimeOfDay": 107,
      "endTimeOfDay": 938,
      "disabled": false
    }
  ]
}