{
  "id": "423",
  "slaId": "458",
  "input": {
    "name": "{{ faker.name.last_name }}",
    "priorities": [
      {
        "id": "502",
        "name": "{{ faker.name.last_name }}"
      },
      {
        "id": "190",
        "name": "{{ faker.name.last_name }}"
      }
    ],
    "reactionTime": "655",
    "resolutionTime": "547"
  },
  "fields": [
    "auxiliary viral Accountability",
    "solution De-engineered Metal"
  ],
  "xJsonMask": [
    "Cotton virtual Pennsylvania",
    "reboot"
  ]
}