{
  "xJsonMask": [
    "Investor China",
    "Extended ADP copy"
  ],
  "fields": [
    "Unbranded disintermediate",
    "open-source Taka bandwidth"
  ],
  "input": {
    "etag": "program",
    "name": {
      "verified": true,
      "givenName": "{{ faker.name.first_name }}",
      "middleName": "parallelism South Carolina",
      "familyName": "{{ faker.name.last_name }}",
      "commonName": "Small Wooden Cheese"
    },
    "about": "Functionality vortals",
    "photos": [
      {
        "etag": "deposit",
        "primary": false,
        "photoId": "432",
        "photoUrl": "synthesizing Rustic Metal Pizza"
      },
      {
        "etag": "Guarani empowering",
        "primary": false,
        "photoId": "106",
        "photoUrl": "grow"
      }
    ],
    "labels": [
      {
        "etag": "Garden & Kids",
        "label": "Optimization Director Gorgeous Rubber Sausages"
      },
      {
        "etag": "Ports",
        "label": "bypassing"
      }
    ],
    "emails": [
      {
        "etag": "Port Agent",
        "primary": true,
        "verified": false,
        "email": "{{ faker.internet.example_email }}",
        "type": {
          "id": "{{ faker.random.uuid }}",
          "type": "{{ faker.database.type }}",
          "name": "{{ faker.name.last_name }}"
        }
      },
      {
        "etag": "evolve Bedfordshire",
        "primary": true,
        "verified": true,
        "email": "{{ faker.internet.example_email }}",
        "type": {
          "id": "{{ faker.random.uuid }}",
          "type": "{{ faker.database.type }}",
          "name": "{{ faker.name.last_name }}"
        }
      }
    ],
    "phones": [
      {
        "etag": "interfaces killer Awesome",
        "primary": false,
        "verified": true,
        "number": "{{ faker.random.ushort }}",
        "type": {
          "id": "{{ faker.random.uuid }}",
          "type": "{{ faker.database.type }}",
          "name": "{{ faker.name.last_name }}"
        }
      },
      {
        "etag": "calculate",
        "primary": false,
        "verified": true,
        "number": "{{ faker.random.ushort }}",
        "type": {
          "id": "{{ faker.random.uuid }}",
          "type": "{{ faker.database.type }}",
          "name": "{{ faker.name.last_name }}"
        }
      }
    ],
    "managers": [
      {
        "etag": "primary",
        "primary": true,
        "user": {
          "id": "{{ faker.random.uuid }}",
          "type": "{{ faker.database.type }}",
          "name": "{{ faker.name.last_name }}"
        }
      },
      {
        "etag": "evolve Latvian Lats channels",
        "primary": true,
        "user": {
          "id": "{{ faker.random.uuid }}",
          "type": "{{ faker.database.type }}",
          "name": "{{ faker.name.last_name }}"
        }
      }
    ],
    "comments": [
      {
        "etag": "USB",
        "text": "{{ faker.lorem.text }}",
        "format": [
          {
            "offset": 781,
            "length": 373,
            "link": {
              "url": "{{ faker.internet.url }}"
            }
          },
          {
            "offset": 580,
            "length": 768,
            "link": {
              "url": "{{ faker.internet.url }}"
            }
          }
        ]
      },
      {
        "etag": "Knolls salmon Berkshire",
        "text": "{{ faker.lorem.text }}",
        "format": [
          {
            "offset": 101,
            "length": 841,
            "link": {
              "url": "{{ faker.internet.url }}"
            }
          },
          {
            "offset": 534,
            "length": 779,
            "link": {
              "url": "{{ faker.internet.url }}"
            }
          }
        ]
      }
    ],
    "languages": [
      {
        "etag": "Executive silver",
        "primary": false,
        "tag": "FTP Electronics & Shoes monetize"
      },
      {
        "etag": "explicit connecting",
        "primary": false,
        "tag": "interactive Tactics"
      }
    ],
    "timezones": [
      {
        "etag": "turquoise",
        "primary": false,
        "timezone": {
          "id": "{{ faker.random.uuid }}",
          "type": "{{ faker.database.type }}",
          "name": "{{ faker.name.last_name }}"
        }
      },
      {
        "etag": "morph technologies",
        "primary": true,
        "timezone": {
          "id": "{{ faker.random.uuid }}",
          "type": "{{ faker.database.type }}",
          "name": "{{ faker.name.last_name }}"
        }
      }
    ],
    "imclients": [
      {
        "protocol": "{{ faker.internet.protocol }}",
        "createdBy": "CSS",
        "externalUser": "Ohio Industrial Jewelery, Garden & Baby",
        "gatewayId": "{{ faker.random.uuid }}",
        "via": "Cook Islands"
      },
      {
        "protocol": "{{ faker.internet.protocol }}",
        "createdBy": "Rubber PNG mission-critical",
        "externalUser": "Plaza",
        "gatewayId": "{{ faker.random.uuid }}",
        "via": "hybrid"
      }
    ],
    "variables": [
      {
        "etag": "Toys & Health",
        "key": "Sleek Granite Soap Music, Baby & Jewelery Supervisor",
        "value": "Home Loan Account Operations vertical"
      },
      {
        "etag": "complexity",
        "key": "Home Loan Account",
        "value": "copying Generic Metal Chicken bypass"
      }
    ]
  }
}