{
  "xJsonMask": [
    "Bedfordshire neural-net",
    "Refined Fresh Ball benchmark Applications"
  ],
  "fields": [
    "Unbranded Cotton Gloves South Dakota Phased",
    "Money Market Account transparent Extended"
  ],
  "input": {
    "etag": "Quality-focused Avon",
    "name": "{{ faker.name.last_name }}",
    "subject": "Generic",
    "description": "mobile Highway",
    "contactInfo": "plum applications RAM",
    "assignee": {
      "id": "719",
      "name": "{{ faker.name.last_name }}"
    },
    "reporter": {
      "id": "994",
      "name": "{{ faker.name.last_name }}"
    },
    "impacted": {
      "id": "510",
      "name": "{{ faker.name.last_name }}"
    },
    "group": {
      "id": "922",
      "name": "{{ faker.name.last_name }}"
    },
    "status": {
      "id": "633",
      "name": "{{ faker.name.last_name }}"
    },
    "closeReason": {
      "id": "226",
      "name": "{{ faker.name.last_name }}"
    },
    "priority": {
      "id": "639",
      "name": "{{ faker.name.last_name }}"
    },
    "source": {
      "id": "446",
      "name": "{{ faker.name.last_name }}"
    },
    "service": {
      "id": "202",
      "name": "{{ faker.name.last_name }}"
    },
    "close": {
      "closeResult": "Incredible Plastic Gloves Operations Shoals"
    },
    "rate": {
      "rating": "291",
      "ratingComment": "Integration Brand Brand"
    },
    "comments": [
      {
        "etag": "Beauty Avon JBOD",
        "text": "{{ faker.lorem.text }}"
      },
      {
        "etag": "Handmade Fresh Keyboard Engineer action-items",
        "text": "{{ faker.lorem.text }}"
      }
    ],
    "links": [
      {
        "etag": "Money Market Account",
        "url": "{{ faker.internet.url }}",
        "name": "{{ faker.name.last_name }}"
      },
      {
        "etag": "Rustic Guyana",
        "url": "{{ faker.internet.url }}",
        "name": "{{ faker.name.last_name }}"
      }
    ],
    "related": [
      {
        "etag": "Borders Garden & Music",
        "relationType": "BlockedBy",
        "relatedTo": {
          "id": "917",
          "ver": 478,
          "etag": "leverage Awesome Soft Bike",
          "createdAt": "373",
          "updatedAt": "285",
          "name": "{{ faker.name.last_name }}",
          "subject": "online client-server parse",
          "description": "revolutionize web services Handcrafted",
          "contactInfo": "Hill Licensed Fresh Towels Incredible Metal Shirt",
          "plannedReactionAt": "975",
          "plannedResolveAt": "506",
          "timing": {
            "resolvedAt": "647",
            "reactedAt": "720",
            "differenceInReaction": "357",
            "differenceInResolve": "605"
          },
          "slaCondition": [
            {
              "id": "217",
              "name": "{{ faker.name.last_name }}",
              "priorities": [
                null,
                null
              ],
              "reactionTime": "767",
              "resolutionTime": "768",
              "slaId": "623",
              "createdAt": "887",
              "updatedAt": "291"
            },
            {
              "id": "679",
              "name": "{{ faker.name.last_name }}",
              "priorities": [
                null,
                null
              ],
              "reactionTime": "802",
              "resolutionTime": "387",
              "slaId": "753",
              "createdAt": "222",
              "updatedAt": "226"
            }
          ],
          "comments": {
            "page": "171",
            "next": true,
            "items": [
              {
                "id": "{{ faker.random.uuid }}",
                "ver": 976,
                "createdAt": "310",
                "updatedAt": "775",
                "text": "{{ faker.lorem.text }}",
                "edited": false,
                "caseId": "979"
              },
              {
                "id": "{{ faker.random.uuid }}",
                "ver": 58,
                "createdAt": "243",
                "updatedAt": "895",
                "text": "{{ faker.lorem.text }}",
                "edited": true,
                "caseId": "357"
              }
            ]
          },
          "related": {
            "page": "946",
            "next": true,
            "items": [
              {
                "id": "904",
                "ver": 445,
                "etag": "partnerships Incredible Concrete Towels Central",
                "createdAt": "814",
                "updatedAt": "242",
                "relationType": "DuplicatedBy"
              },
              {
                "id": "964",
                "ver": 893,
                "etag": "Upgradable overriding",
                "createdAt": "955",
                "updatedAt": "549",
                "relationType": "RelatesTo"
              }
            ]
          },
          "links": {
            "page": "892",
            "next": true,
            "items": [
              {
                "id": "856",
                "ver": 231,
                "etag": "haptic",
                "createdAt": "622",
                "updatedAt": "724",
                "name": "{{ faker.name.last_name }}",
                "url": "{{ faker.internet.url }}"
              },
              {
                "id": "11",
                "ver": 48,
                "etag": "Auto Loan Account coherent",
                "createdAt": "356",
                "updatedAt": "649",
                "name": "{{ faker.name.last_name }}",
                "url": "{{ faker.internet.url }}"
              }
            ]
          },
          "files": {
            "page": "373",
            "next": false,
            "items": [
              {
                "id": "395",
                "createdAt": "570",
                "size": "286",
                "mime": "Somali Shilling",
                "name": "{{ faker.name.last_name }}"
              },
              {
                "id": "71",
                "createdAt": "67",
                "size": "13",
                "mime": "primary",
                "name": "{{ faker.name.last_name }}"
              }
            ]
          }
        }
      },
      {
        "etag": "Qatar",
        "relationType": "Blocks",
        "relatedTo": {
          "id": "561",
          "ver": 598,
          "etag": "bifurcated",
          "createdAt": "160",
          "updatedAt": "800",
          "name": "{{ faker.name.last_name }}",
          "subject": "Cotton",
          "description": "embrace Checking Account",
          "contactInfo": "payment",
          "plannedReactionAt": "684",
          "plannedResolveAt": "45",
          "timing": {
            "resolvedAt": "395",
            "reactedAt": "765",
            "differenceInReaction": "437",
            "differenceInResolve": "565"
          },
          "slaCondition": [
            {
              "id": "396",
              "name": "{{ faker.name.last_name }}",
              "priorities": [
                null,
                null
              ],
              "reactionTime": "997",
              "resolutionTime": "776",
              "slaId": "177",
              "createdAt": "305",
              "updatedAt": "400"
            },
            {
              "id": "755",
              "name": "{{ faker.name.last_name }}",
              "priorities": [
                null,
                null
              ],
              "reactionTime": "232",
              "resolutionTime": "692",
              "slaId": "757",
              "createdAt": "738",
              "updatedAt": "805"
            }
          ],
          "comments": {
            "page": "58",
            "next": true,
            "items": [
              {
                "id": "{{ faker.random.uuid }}",
                "ver": 686,
                "createdAt": "190",
                "updatedAt": "443",
                "text": "{{ faker.lorem.text }}",
                "edited": false,
                "caseId": "316"
              },
              {
                "id": "{{ faker.random.uuid }}",
                "ver": 420,
                "createdAt": "510",
                "updatedAt": "969",
                "text": "{{ faker.lorem.text }}",
                "edited": true,
                "caseId": "189"
              }
            ]
          },
          "related": {
            "page": "799",
            "next": true,
            "items": [
              {
                "id": "687",
                "ver": 222,
                "etag": "Buckinghamshire Interactions withdrawal",
                "createdAt": "52",
                "updatedAt": "464",
                "relationType": "Blocks"
              },
              {
                "id": "207",
                "ver": 262,
                "etag": "Infrastructure",
                "createdAt": "758",
                "updatedAt": "11",
                "relationType": "Duplicates"
              }
            ]
          },
          "links": {
            "page": "814",
            "next": true,
            "items": [
              {
                "id": "291",
                "ver": 735,
                "etag": "Pre-emptive withdrawal deposit",
                "createdAt": "508",
                "updatedAt": "14",
                "name": "{{ faker.name.last_name }}",
                "url": "{{ faker.internet.url }}"
              },
              {
                "id": "760",
                "ver": 171,
                "etag": "killer platforms",
                "createdAt": "386",
                "updatedAt": "504",
                "name": "{{ faker.name.last_name }}",
                "url": "{{ faker.internet.url }}"
              }
            ]
          },
          "files": {
            "page": "936",
            "next": true,
            "items": [
              {
                "id": "345",
                "createdAt": "626",
                "size": "558",
                "mime": "Loaf",
                "name": "{{ faker.name.last_name }}"
              },
              {
                "id": "717",
                "createdAt": "283",
                "size": "729",
                "mime": "Checking Account orange Incredible Wooden Chips",
                "name": "{{ faker.name.last_name }}"
              }
            ]
          }
        }
      }
    ]
  }
}